pantrypy/__init__.py
pantrypy/color_structures.py
pantrypy/commons.py
pantrypy/geometry_structures.py
pantrypy/metadata.py
pantrypy/internals/__init__.py
pantrypy/internals/constants.py
pantrypy/internals/operation_engine.py
pantrypy/internals/resources.py
pantrypy/internals/utils.py
PantryPy-1.0.1a6.dist-info/LICENSE
PantryPy-1.0.1a6.dist-info/METADATA
PantryPy-1.0.1a6.dist-info/WHEEL
PantryPy-1.0.1a6.dist-info/top_level.txt
PantryPy-1.0.1a6.dist-info/RECORD
